{
  "summary": {
    "total_problems": 6,
    "successful_generations": 6,
    "solved_total": 6,
    "overall_solve_rate": 1.0,
    "wall_clock_seconds": 7.0,
    "workers": 4
  },
  "criterion_3_5": {
    "depth_le_10_total": 6,
    "depth_le_10_solved": 6,
    "depth_le_10_rate": 1.0,
    "threshold": 0.9,
    "passed": true
  },
  "per_depth": {
    "5": {
      "total_problems": 6,
      "generated": 6,
      "solved": 6,
      "solve_rate_among_generated": 1.0,
      "solve_rate_overall": 1.0,
      "nodes_expanded_median": 5.0,
      "nodes_expanded_p95": 9.65,
      "productive_middle_count": 0
    }
  },
  "per_template": {
    "linear": {
      "total_problems": 3,
      "generated": 3,
      "solved": 3,
      "solve_rate_among_generated": 1.0
    },
    "quadratic": {
      "total_problems": 3,
      "generated": 3,
      "solved": 3,
      "solve_rate_among_generated": 1.0
    }
  },
  "rule_application_counts": {
    "ADD_TO_BOTH_SIDES": 77,
    "COLLECT_LIKE_VARIABLE_TERMS_AT": 93,
    "COMBINE_LIKE_TERMS_AT": 7,
    "COMPLETE_THE_SQUARE": 1,
    "DISTRIBUTE_OVER_SUBTREE": 87,
    "DIVIDE_BOTH_SIDES_BY": 9,
    "FLIP_SIDES": 22,
    "MOVE_ALL_TO_LHS": 21,
    "MOVE_ALL_TO_RHS": 18,
    "MULTIPLY_BOTH_SIDES_BY": 18,
    "NEGATE_BOTH_SIDES": 22,
    "POLYNOMIAL_LONG_DIVISION": 7,
    "RECIPROCATE_BOTH_SIDES": 22,
    "EXPAND_PRODUCT": 3,
    "FACTOR_OUT_GCF_AT": 37,
    "ISOLATE_VARIABLE": 2,
    "POLY_TO_MONIC": 9,
    "SIMPLIFY_AT": 10,
    "CLEAR_FRACTIONS_BY_LCD": 9,
    "COMBINE_FRACTIONS_AT": 11,
    "CROSS_MULTIPLY": 1,
    "PARTIAL_FRACTIONS": 1,
    "VIETAS_FORMULAS": 1
  },
  "dead_rules": [
    "CANCEL_COMMON_FACTOR",
    "COMMON_DENOMINATOR_AT",
    "DISTRIBUTE_NEGATIVE_AT",
    "DOUBLE_NEGATION_AT",
    "EXPAND_POWER",
    "FACTOR_BY_GROUPING",
    "FACTOR_DIFFERENCE_OF_SQUARES_AT",
    "FACTOR_POLYNOMIAL",
    "IDENTITY_ADD_ZERO_AT",
    "IDENTITY_MUL_ONE_AT",
    "PERFECT_SQUARE_TRINOMIAL_AT",
    "POW_OF_POW_AT",
    "POW_PRODUCT_AT",
    "POW_QUOTIENT_AT",
    "QUADRATIC_FORMULA",
    "RATIONAL_ROOT_THEOREM",
    "SIMPLIFY_NUMERIC_AT",
    "SPLIT_FRACTION_AT",
    "SQRT_BOTH_SIDES",
    "SQUARE_BOTH_SIDES",
    "SYNTHETIC_DIVISION",
    "ZERO_PROPERTY_AT"
  ]
}